{
"meta":{"test_sets":[],"test_metrics":[],"learn_metrics":[{"best_value":"Min","name":"RMSE"}],"launch_mode":"Train","parameters":"","iteration_count":100,"learn_sets":["learn"],"name":"experiment"},
"iterations":[
{"learn":[6323.797624],"iteration":0,"passed_time":0.003930111404,"remaining_time":0.389081029},
{"learn":[5951.648115],"iteration":1,"passed_time":0.007156556405,"remaining_time":0.3506712639},
{"learn":[5594.713892],"iteration":2,"passed_time":0.01028417676,"remaining_time":0.3325217153},
{"learn":[5269.981427],"iteration":3,"passed_time":0.01354578224,"remaining_time":0.3250987738},
{"learn":[4954.841185],"iteration":4,"passed_time":0.01720047741,"remaining_time":0.3268090707},
{"learn":[4710.150631],"iteration":5,"passed_time":0.02031740498,"remaining_time":0.3183060113},
{"learn":[4477.329491],"iteration":6,"passed_time":0.02367015602,"remaining_time":0.31447493},
{"learn":[4276.151079],"iteration":7,"passed_time":0.0269865165,"remaining_time":0.3103449398},
{"learn":[4080.348712],"iteration":8,"passed_time":0.02999251922,"remaining_time":0.3032576943},
{"learn":[3889.368418],"iteration":9,"passed_time":0.03117825883,"remaining_time":0.2806043295},
{"learn":[3711.164233],"iteration":10,"passed_time":0.03229437153,"remaining_time":0.2612908242},
{"learn":[3562.987599],"iteration":11,"passed_time":0.03344034664,"remaining_time":0.2452292087},
{"learn":[3425.732242],"iteration":12,"passed_time":0.03457718916,"remaining_time":0.231401189},
{"learn":[3277.050032],"iteration":13,"passed_time":0.0357447517,"remaining_time":0.2195749033},
{"learn":[3160.232876],"iteration":14,"passed_time":0.0368526095,"remaining_time":0.2088314538},
{"learn":[3045.940338],"iteration":15,"passed_time":0.03800740493,"remaining_time":0.1995388759},
{"learn":[2919.177917],"iteration":16,"passed_time":0.03917994361,"remaining_time":0.1912903129},
{"learn":[2824.694031],"iteration":17,"passed_time":0.04033762859,"remaining_time":0.183760308},
{"learn":[2748.905389],"iteration":18,"passed_time":0.04151845823,"remaining_time":0.176999743},
{"learn":[2662.273936],"iteration":19,"passed_time":0.04264198942,"remaining_time":0.1705679577},
{"learn":[2582.81631],"iteration":20,"passed_time":0.04375252264,"remaining_time":0.1645928233},
{"learn":[2518.99915],"iteration":21,"passed_time":0.04489868064,"remaining_time":0.1591862314},
{"learn":[2452.140406],"iteration":22,"passed_time":0.0460230884,"remaining_time":0.1540772959},
{"learn":[2389.152838],"iteration":23,"passed_time":0.04717240918,"remaining_time":0.1493792957},
{"learn":[2340.106339],"iteration":24,"passed_time":0.04830334435,"remaining_time":0.1449100331},
{"learn":[2276.919065],"iteration":25,"passed_time":0.04945009343,"remaining_time":0.1407425736},
{"learn":[2228.346564],"iteration":26,"passed_time":0.05058091707,"remaining_time":0.1367558128},
{"learn":[2183.607838],"iteration":27,"passed_time":0.05174214625,"remaining_time":0.1330512332},
{"learn":[2143.572942],"iteration":28,"passed_time":0.0524203643,"remaining_time":0.1283395126},
{"learn":[2104.983184],"iteration":29,"passed_time":0.0536880563,"remaining_time":0.1252721314},
{"learn":[2068.246193],"iteration":30,"passed_time":0.05485398058,"remaining_time":0.1220943439},
{"learn":[2033.781486],"iteration":31,"passed_time":0.05600318092,"remaining_time":0.1190067595},
{"learn":[2005.89685],"iteration":32,"passed_time":0.05718130688,"remaining_time":0.1160953806},
{"learn":[1978.566198],"iteration":33,"passed_time":0.05835307159,"remaining_time":0.1132736096},
{"learn":[1945.222308],"iteration":34,"passed_time":0.05947816186,"remaining_time":0.1104594435},
{"learn":[1912.947025],"iteration":35,"passed_time":0.0606256771,"remaining_time":0.1077789815},
{"learn":[1887.71526],"iteration":36,"passed_time":0.06179477307,"remaining_time":0.1052181271},
{"learn":[1858.310446],"iteration":37,"passed_time":0.06294118647,"remaining_time":0.1026935148},
{"learn":[1841.220755],"iteration":38,"passed_time":0.06407589779,"remaining_time":0.100221276},
{"learn":[1808.083033],"iteration":39,"passed_time":0.06521007715,"remaining_time":0.09781511573},
{"learn":[1790.680902],"iteration":40,"passed_time":0.06635056647,"remaining_time":0.09548008345},
{"learn":[1769.684129],"iteration":41,"passed_time":0.06748016522,"remaining_time":0.09318689483},
{"learn":[1748.304456],"iteration":42,"passed_time":0.06948194588,"remaining_time":0.09210397477},
{"learn":[1728.540093],"iteration":43,"passed_time":0.07119330121,"remaining_time":0.09060965609},
{"learn":[1718.316902],"iteration":44,"passed_time":0.07279250458,"remaining_time":0.0889686167},
{"learn":[1695.205811],"iteration":45,"passed_time":0.07442418258,"remaining_time":0.08736751868},
{"learn":[1681.793842],"iteration":46,"passed_time":0.07595953368,"remaining_time":0.08565649542},
{"learn":[1657.742486],"iteration":47,"passed_time":0.07713360133,"remaining_time":0.08356140144},
{"learn":[1649.134931],"iteration":48,"passed_time":0.07765208109,"remaining_time":0.08082155379},
{"learn":[1628.713913],"iteration":49,"passed_time":0.07884984619,"remaining_time":0.07884984619},
{"learn":[1605.756741],"iteration":50,"passed_time":0.07997728401,"remaining_time":0.07684091993},
{"learn":[1578.111557],"iteration":51,"passed_time":0.08109709257,"remaining_time":0.07485885468},
{"learn":[1564.917659],"iteration":52,"passed_time":0.08236993022,"remaining_time":0.07304503246},
{"learn":[1542.969865],"iteration":53,"passed_time":0.08355094908,"remaining_time":0.0711730307},
{"learn":[1527.028336],"iteration":54,"passed_time":0.08472539591,"remaining_time":0.06932077847},
{"learn":[1520.411421],"iteration":55,"passed_time":0.08586073511,"remaining_time":0.06746200615},
{"learn":[1510.728577],"iteration":56,"passed_time":0.08699893449,"remaining_time":0.06563077514},
{"learn":[1493.357553],"iteration":57,"passed_time":0.08821084176,"remaining_time":0.06387681645},
{"learn":[1482.325073],"iteration":58,"passed_time":0.08936695874,"remaining_time":0.06210246285},
{"learn":[1463.185538],"iteration":59,"passed_time":0.09051596391,"remaining_time":0.06034397594},
{"learn":[1449.248547],"iteration":60,"passed_time":0.09162656628,"remaining_time":0.05858091943},
{"learn":[1439.365934],"iteration":61,"passed_time":0.09276719054,"remaining_time":0.05685731033},
{"learn":[1424.681446],"iteration":62,"passed_time":0.0939031208,"remaining_time":0.0551494519},
{"learn":[1411.246651],"iteration":63,"passed_time":0.09504258968,"remaining_time":0.0534614567},
{"learn":[1404.208467],"iteration":64,"passed_time":0.09621405105,"remaining_time":0.05180756595},
{"learn":[1395.114799],"iteration":65,"passed_time":0.09754112996,"remaining_time":0.05024846089},
{"learn":[1384.128367],"iteration":66,"passed_time":0.09864177336,"remaining_time":0.04858475404},
{"learn":[1367.267971],"iteration":67,"passed_time":0.09975839571,"remaining_time":0.04694512739},
{"learn":[1362.752223],"iteration":68,"passed_time":0.1008806154,"remaining_time":0.04532317503},
{"learn":[1358.116098],"iteration":69,"passed_time":0.1019828967,"remaining_time":0.04370695572},
{"learn":[1345.143752],"iteration":70,"passed_time":0.103130955,"remaining_time":0.04212391121},
{"learn":[1338.950101],"iteration":71,"passed_time":0.1042232833,"remaining_time":0.04053127684},
{"learn":[1335.593889],"iteration":72,"passed_time":0.1053004835,"remaining_time":0.03894675419},
{"learn":[1332.510778],"iteration":73,"passed_time":0.1064245389,"remaining_time":0.03739240555},
{"learn":[1329.392277],"iteration":74,"passed_time":0.1075389821,"remaining_time":0.03584632736},
{"learn":[1314.926646],"iteration":75,"passed_time":0.1086371887,"remaining_time":0.03430648065},
{"learn":[1307.076778],"iteration":76,"passed_time":0.1097160551,"remaining_time":0.03277232814},
{"learn":[1303.530052],"iteration":77,"passed_time":0.1108424617,"remaining_time":0.03126325843},
{"learn":[1300.24561],"iteration":78,"passed_time":0.1119998746,"remaining_time":0.02977211856},
{"learn":[1296.467526],"iteration":79,"passed_time":0.1131266488,"remaining_time":0.02828166221},
{"learn":[1289.666432],"iteration":80,"passed_time":0.1142230365,"remaining_time":0.02679305795},
{"learn":[1286.70076],"iteration":81,"passed_time":0.1152864894,"remaining_time":0.02530679035},
{"learn":[1283.659239],"iteration":82,"passed_time":0.1163938052,"remaining_time":0.02383969503},
{"learn":[1279.028588],"iteration":83,"passed_time":0.1176018738,"remaining_time":0.02240035692},
{"learn":[1276.572997],"iteration":84,"passed_time":0.1186791755,"remaining_time":0.02094338392},
{"learn":[1260.044609],"iteration":85,"passed_time":0.1198047487,"remaining_time":0.01950309863},
{"learn":[1256.062089],"iteration":86,"passed_time":0.1209191228,"remaining_time":0.01806837467},
{"learn":[1251.803257],"iteration":87,"passed_time":0.1220094704,"remaining_time":0.01663765505},
{"learn":[1249.773233],"iteration":88,"passed_time":0.1231219731,"remaining_time":0.01521732252},
{"learn":[1247.829578],"iteration":89,"passed_time":0.1242043603,"remaining_time":0.01380048447},
{"learn":[1236.525661],"iteration":90,"passed_time":0.1254305,"remaining_time":0.01240521429},
{"learn":[1234.744181],"iteration":91,"passed_time":0.1284841865,"remaining_time":0.01117253796},
{"learn":[1220.780692],"iteration":92,"passed_time":0.1301264372,"remaining_time":0.009794463016},
{"learn":[1217.46138],"iteration":93,"passed_time":0.1314982367,"remaining_time":0.008393504469},
{"learn":[1215.579234],"iteration":94,"passed_time":0.1332593534,"remaining_time":0.007013650179},
{"learn":[1213.847038],"iteration":95,"passed_time":0.1345845792,"remaining_time":0.005607690799},
{"learn":[1202.322324],"iteration":96,"passed_time":0.1359132618,"remaining_time":0.004203502941},
{"learn":[1201.022981],"iteration":97,"passed_time":0.137266747,"remaining_time":0.002801362184},
{"learn":[1189.661124],"iteration":98,"passed_time":0.1386732913,"remaining_time":0.001400740317},
{"learn":[1176.826885],"iteration":99,"passed_time":0.1400207027,"remaining_time":0}
]}